petit_type_system/__init__.py
petit_type_system/ast_utils.py
petit_type_system/const.py
petit_type_system/default_handlers.py
petit_type_system/exceptions.py
petit_type_system/inline_type.py
petit_type_system/named_types.py
petit_type_system/petit_type_system.py
petit_type_system/store.py
petit_type_system/type_spoofer.py
petit_type_system/utils.py
petit_type_system-0.3.0.dist-info/LICENSE.txt
petit_type_system-0.3.0.dist-info/METADATA
petit_type_system-0.3.0.dist-info/WHEEL
petit_type_system-0.3.0.dist-info/top_level.txt
petit_type_system-0.3.0.dist-info/RECORD
